torchConvNd/__init__.py
torchConvNd/convNd.py
torchConvNd/convNdAuto.py
torchConvNd/convNdFunc.py
torchConvNd/convNdRec.py
torchConvNd/utils/__init__.py
torchConvNd/utils/utils.py
torchConvNd-0.2.0.dist-info/LICENSE
torchConvNd-0.2.0.dist-info/METADATA
torchConvNd-0.2.0.dist-info/WHEEL
torchConvNd-0.2.0.dist-info/top_level.txt
torchConvNd-0.2.0.dist-info/RECORD
