Metadata-Version: 2.1
Name: torchConvNd
Version: 0.2.0
Summary: a library to create convolution from any torch network
Home-page: https://github.com/jolatechno/torchConvNd
Author: Joseph TOUZET
Author-email: joseph.touzet@gmail.com
License: UNKNOWN
Platform: UNKNOWN
Classifier: Programming Language :: Python :: 3
Classifier: License :: OSI Approved :: GNU General Public License v3 (GPLv3)
Classifier: Operating System :: OS Independent
Requires-Python: >=3.6
Requires-Dist: numpy (>=1.18.0)
Requires-Dist: torch (>=1.3.1)
